configs/prod.toml
mcme/__init__.py
mcme/assets.py
mcme/auth.py
mcme/avatars.py
mcme/commands.py
mcme/constants.py
mcme/helpers.py
mcme/logger.py
mcme/main.py
mcme/mocked.py
mcme/motions.py
mcme/scenes.py
mcme/schemas.py
mcme/state.py
mcme/user.py
openapi_client/__init__.py
openapi_client/api/__init__.py
openapi_client/api/assets_api.py
openapi_client/api/avatars_api.py
openapi_client/api/blend_motions_api.py
openapi_client/api/create_avatar_from_images_api.py
openapi_client/api/create_avatar_from_measurements_api.py
openapi_client/api/create_avatar_from_scans_api.py
openapi_client/api/create_avatar_from_video_api.py
openapi_client/api/create_avatars_from_betas_api.py
openapi_client/api/create_scene_from_video_api.py
openapi_client/api/credit_bundles_api.py
openapi_client/api/helpers_api.py
openapi_client/api/images_api.py
openapi_client/api/info_api.py
openapi_client/api/measure_avatar_api.py
openapi_client/api/mesh_api.py
openapi_client/api/motions_api.py
openapi_client/api/scenes_api.py
openapi_client/api/search_motions_api.py
openapi_client/api/subscription_api.py
openapi_client/api/teams_api.py
openapi_client/api/user_api.py
openapi_client/api/videos_api.py
openapi_client/api_client.py
openapi_client/api_response.py
openapi_client/configuration.py
openapi_client/exceptions.py
openapi_client/models/__init__.py
openapi_client/models/docschemas_doc_afi_inputs.py
openapi_client/models/docschemas_doc_afm_inputs.py
openapi_client/models/docschemas_doc_afs_inputs.py
openapi_client/models/docschemas_doc_afv_inputs.py
openapi_client/models/docschemas_doc_asset_response.py
openapi_client/models/docschemas_doc_avatar_attributes.py
openapi_client/models/docschemas_doc_avatar_link.py
openapi_client/models/docschemas_doc_avatar_metadata.py
openapi_client/models/docschemas_doc_avatar_relationships.py
openapi_client/models/docschemas_doc_avatar_relationships_exported_mesh.py
openapi_client/models/docschemas_doc_avatar_relationships_exported_mesh_data_inner.py
mcme-1.2.1.dist-info/METADATA
mcme-1.2.1.dist-info/WHEEL
mcme-1.2.1.dist-info/entry_points.txt
mcme-1.2.1.dist-info/RECORD
