Metadata-Version: 2.1
Name: mcme
Version: 1.2.1
Summary: 
Author: antonia7
Author-email: antonia@meshcapade.com
Requires-Python: >=3.10,<4.0
Classifier: Programming Language :: Python :: 3
Classifier: Programming Language :: Python :: 3.10
Classifier: Programming Language :: Python :: 3.11
Classifier: Programming Language :: Python :: 3.12
Requires-Dist: aenum (>=3.1.11)
Requires-Dist: click (>=8.1.6,<9.0.0)
Requires-Dist: mypy (>=1.5.1,<2.0.0)
Requires-Dist: pydantic (>=1.10.5,<2)
Requires-Dist: pytest (>=7.4.2,<8.0.0)
Requires-Dist: pytest-cov (>=4.1.0,<5.0.0)
Requires-Dist: python-dateutil (>=2.5.3)
Requires-Dist: python-keycloak (>=3.3.0,<4.0.0)
Requires-Dist: requests (>=2.31.0,<3.0.0)
Requires-Dist: rich (>=13.9.4,<14.0.0)
Requires-Dist: ruff (>=0.9.6,<0.10.0)
Requires-Dist: setuptools (>=21.0.0)
Requires-Dist: six (>=1.17.0,<2.0.0)
Requires-Dist: smplcodec (>=2.0.1,<3.0.0)
Requires-Dist: tomli (>=2.0.1,<3.0.0)
Requires-Dist: types-requests (>=2.32.0.20241016,<3.0.0.0)
Requires-Dist: typing-extensions (>=4.12.2,<5.0.0)
Requires-Dist: urllib3 (>=1.25.3,<2.1.0)
